spo4onnx/__init__.py
spo4onnx/__main__.py
spo4onnx/onnx_partial_optimization.py
spo4onnx-1.0.5.dist-info/LICENSE
spo4onnx-1.0.5.dist-info/METADATA
spo4onnx-1.0.5.dist-info/WHEEL
spo4onnx-1.0.5.dist-info/entry_points.txt
spo4onnx-1.0.5.dist-info/top_level.txt
spo4onnx-1.0.5.dist-info/RECORD
