Metadata-Version: 2.1
Name: spo4onnx
Version: 1.0.5
Summary: Simple tool for partial optimization of ONNX. Further optimize some models that cannot be optimized with onnx-optimizer and onnxsim by several tens of percent. In particular, models containing Einsum and OneHot.
Home-page: https://github.com/PINTO0309/spo4onnx
Author: Katsuya Hyodo
Author-email: rmsdh122@yahoo.co.jp
License: MIT License
Platform: linux
Platform: unix
Requires-Python: >=3.6
License-File: LICENSE
